{
    "0x0000..0x8000": {
        "field": "game_pak",
        "mapping_type": "ReadWrite",
        "full_address": true
    },
    "0x8000..0x9800": {
        "field": "bridge.lcd_controller.character_data",
        "mapping_type": "ReadWrite"
    },
    "0x9800..0x9C00": {
        "field": "bridge.lcd_controller.background_display_data_1",
        "mapping_type": "ReadWrite"
    },
    "0x9C00..0xA000": {
        "field": "bridge.lcd_controller.background_display_data_2",
        "mapping_type": "ReadWrite"
    },
    "0xA000..0xC000": {
        "field": "game_pak",
        "mapping_type": "ReadWrite",
        "full_address": true
    },
    "0xC000..0xDE00": {
        "field": "bridge.internal_ram_a",
        "mapping_type": "ReadWrite"
    },
    "0xDE00..0xE000": {
        "field": "bridge.internal_ram_b",
        "mapping_type": "ReadWrite"
    },
    "0xE000..0xFE00": {
        "field": "bridge.internal_ram_a",
        "mapping_type": "ReadWrite"
    },
    "0xFE00..0xFEA0": {
        "field": "bridge.lcd_controller.oam_data",
        "mapping_type": "ReadWrite"
    },
    "0xFEA0..0xFF00": {
        "field": "bridge.lcd_controller.unusable_memory",
        "mapping_type": "ReadWrite"
    },
    "0xFF00": {
        "field": "joypad",
        "mapping_type": "ReadWrite"
    },
    "0xFF01": {
        "field": "bridge.registers.serial_transfer_data",
        "mapping_type": "ReadWrite"
    },
    "0xFF02": {
        "field": "bridge.registers.serial_transfer_control",
        "mapping_type": "Read"
    },
    "0xFF04": {
        "field": "bridge.registers.divider",
        "mapping_type": "ReadWrite"
    },
    "0xFF05": {
        "field": "bridge.timer.counter",
        "mapping_type": "ReadWrite"
    },
    "0xFF06": {
        "field": "bridge.timer.modulo",
        "mapping_type": "ReadWrite"
    },
    "0xFF07": {
        "field": "bridge.timer.control",
        "mapping_type": "ReadWrite"
    },
    "0xFF0F": {
        "field": "bridge.registers.interrupt_flag",
        "mapping_type": "ReadWrite"
    },
    "0xFF10..0xFF40": {
        "field": "bridge.sound_controller",
        "mapping_type": "ReadWrite",
        "full_address": true
    },
    "0xFF40": {
        "field": "bridge.lcd_controller",
        "with": "bridge.scheduler",
        "mapping_type": "ReadWrite"
    },
    "0xFF41": {
        "field": "bridge.lcd_controller.registers.stat",
        "mapping_type": "ReadWrite"
    },
    "0xFF42": {
        "field": "bridge.lcd_controller.registers.scy",
        "mapping_type": "ReadWrite"
    },
    "0xFF43": {
        "field": "bridge.lcd_controller.registers.scx",
        "mapping_type": "ReadWrite"
    },
    "0xFF44": {
        "field": "bridge.lcd_controller.registers.ly",
        "mapping_type": "ReadWrite"
    },
    "0xFF45": {
        "field": "bridge.lcd_controller.registers.lyc",
        "mapping_type": "ReadWrite"
    },
    "0xFF46": {
        "field": "bridge.lcd_controller.registers.dma",
        "mapping_type": "ReadWrite"
    },
    "0xFF47": {
        "field": "bridge.lcd_controller.registers.bgp",
        "mapping_type": "ReadWrite"
    },
    "0xFF48": {
        "field": "bridge.lcd_controller.registers.obp0",
        "mapping_type": "ReadWrite"
    },
    "0xFF49": {
        "field": "bridge.lcd_controller.registers.obp1",
        "mapping_type": "ReadWrite"
    },
    "0xFF4A": {
        "field": "bridge.lcd_controller.registers.wy",
        "mapping_type": "ReadWrite"
    },
    "0xFF4B": {
        "field": "bridge.lcd_controller.registers.wx",
        "mapping_type": "ReadWrite"
    },
    "0xFF80..0xFFFF": {
        "field": "bridge.high_ram",
        "mapping_type": "ReadWrite"
    },
    "0xFFFF": {
        "field": "bridge.registers.interrupt_enable",
        "mapping_type": "ReadWrite"
    }
}
